README.rst
setup.py
slouch/__init__.py
slouch/_version.py
slouch/testing.py
slouch.egg-info/PKG-INFO
slouch.egg-info/SOURCES.txt
slouch.egg-info/dependency_links.txt
slouch.egg-info/not-zip-safe
slouch.egg-info/requires.txt
slouch.egg-info/top_level.txt