Metadata-Version: 1.1
Name: slouch
Version: 0.4.2
Summary: A lightweight framework for building cli-inspired Slack bots.
Home-page: https://github.com/venmo/slouch
Author: Simon Weber
Author-email: simon@venmo.com
License: MIT
Platform: UNKNOWN
Classifier: Development Status :: 4 - Beta
Classifier: Intended Audience :: Developers
Classifier: License :: OSI Approved :: MIT License
Classifier: Programming Language :: Python
Classifier: Programming Language :: Python :: 2.7
